<?xml version="1.0"?>

<!DOCTYPE hibernate-mapping PUBLIC
        "-//Hibernate/Hibernate Mapping DTD 3.0//EN"
        "http://www.hibernate.org/dtd/hibernate-mapping-3.0.dtd">

<hibernate-mapping package="org.dddml.wms.domain.inventoryitem">
  
  <class name="AbstractInventoryItemEvent" table="InventoryItemEvents" mutable="false" abstract="true">

	<composite-id name="inventoryItemEventId" class="org.dddml.wms.domain.inventoryitem.InventoryItemEventId">
		<key-property name="inventoryItemIdProductId" ><column name="ProductId" length="60" sql-type="VARCHAR(60)" /></key-property>
		<key-property name="inventoryItemIdLocatorId" ><column name="LocatorId" length="50" /></key-property>
		<key-property name="inventoryItemIdAttributeSetInstanceId" ><column name="AttributeSetInstanceId" length="50" /></key-property>
		<key-property name="version" ></key-property>
	</composite-id>

    <discriminator column="EventType" type="string" />


    <property name="createdBy" column="CreatedBy"/>

    <property name="createdAt" column="CreatedAt" />

    <property name="commandId" column="CommandId"/>

        <subclass name="AbstractInventoryItemEvent$AbstractInventoryItemStateEvent" abstract="true">

	<property name="onHandQuantity" ><column name="OnHandQuantity" sql-type="decimal(18,6)" /></property>
	<property name="inTransitQuantity" ><column name="InTransitQuantity" sql-type="decimal(18,6)" /></property>
	<property name="reservedQuantity" ><column name="ReservedQuantity" sql-type="decimal(18,6)" /></property>
	<property name="occupiedQuantity" ><column name="OccupiedQuantity" sql-type="decimal(18,6)" /></property>
	<property name="virtualQuantity" ><column name="VirtualQuantity" sql-type="decimal(18,6)" /></property>

    <subclass name="AbstractInventoryItemEvent$SimpleInventoryItemStateCreated" discriminator-value="Created">
    	
    </subclass>

    <subclass name="AbstractInventoryItemEvent$SimpleInventoryItemStateMergePatched" discriminator-value="MergePatched">

        <property name="isPropertyOnHandQuantityRemoved" column="IsPropertyOnHandQuantityRemoved"/>

        <property name="isPropertyInTransitQuantityRemoved" column="IsPropertyInTransitQuantityRemoved"/>

        <property name="isPropertyReservedQuantityRemoved" column="IsPropertyReservedQuantityRemoved"/>

        <property name="isPropertyOccupiedQuantityRemoved" column="IsPropertyOccupiedQuantityRemoved"/>

        <property name="isPropertyVirtualQuantityRemoved" column="IsPropertyVirtualQuantityRemoved"/>


    </subclass>

        </subclass>

  </class>
  
</hibernate-mapping>
